fidding_flask-1.1.dev0.dist-info/LICENSE.txt
fidding_flask-1.1.dev0.dist-info/METADATA
fidding_flask-1.1.dev0.dist-info/RECORD
fidding_flask-1.1.dev0.dist-info/WHEEL
fidding_flask-1.1.dev0.dist-info/entry_points.txt
fidding_flask-1.1.dev0.dist-info/top_level.txt
flask/__init__.py
flask/__main__.py
flask/_compat.py
flask/app.py
flask/blueprints.py
flask/cli.py
flask/config.py
flask/ctx.py
flask/debughelpers.py
flask/globals.py
flask/helpers.py
flask/logging.py
flask/sessions.py
flask/signals.py
flask/templating.py
flask/testing.py
flask/views.py
flask/wrappers.py
flask/json/__init__.py
flask/json/tag.py
